{"content": {"Tinker Lab": {"para_sentences": {"para_0": "This is another one of the more abstract topics in this course, but hopefully these examples help you get a sense of it. Come back and take another look after going through the Exploration on object references and identity.", "para_1": "Compare the behavior of the following two code examples:", "para_2": "", "para_3": "", "para_4": "How might you explain this behavior?", "para_5": "\u00a0", "para_6": "Now compare the behavior of these two code examples:", "para_7": "", "para_8": "", "para_9": "How might you explain this behavior?", "para_10": "What does the is operator do?", "para_11": "\u00a0", "para_12": "And now compare these two:", "para_13": "", "para_14": "", "para_15": "How might you explain this behavior?", "para_16": "\u00a0"}, "li_sentences": {}}}, "heading_sentences": ["Additional examples for Module 7 - part 2"], "__pre_h2__": {"pre_h2_para_sentences": {"para_0": ""}, "pre_h2_li_sentences": {}}, "content_links": {"para_0": [0], "para_1": [0], "para_2": [0], "para_3": [0], "para_4": [0], "para_5": [0], "para_6": [0], "para_7": [0], "para_8": [0], "para_9": [0], "para_10": [0], "para_11": [0], "para_12": [0], "para_13": [0], "para_14": [0], "para_15": [0], "para_16": [0]}, "preh2_links": {"para_0": [0]}}